stimekeeper/NoTime.py
stimekeeper/__init__.py
stimekeeper-0.0.2.dist-info/LICENSE
stimekeeper-0.0.2.dist-info/METADATA
stimekeeper-0.0.2.dist-info/WHEEL
stimekeeper-0.0.2.dist-info/top_level.txt
stimekeeper-0.0.2.dist-info/RECORD
