Metadata-Version: 2.1
Name: stimekeeper
Version: 0.0.2
Summary: Times Up Philosophy. Think of yourself as dead
Home-page: https://github.com/strat365/timekeeper
Author: Strat 365
Author-email: Ron@Diasly.com
License: UNKNOWN
Platform: UNKNOWN
Classifier: Programming Language :: Python :: 3
Classifier: License :: OSI Approved :: MIT License
Classifier: Operating System :: OS Independent
Requires-Python: >=3.6
Requires-Dist: flask
Requires-Dist: flask-restful
Requires-Dist: flask-swagger-ui
